viessmann_data_audit/__init__.py
viessmann_data_audit/data_audit.py
viessmann_data_audit-0.1.8.dist-info/LICENSE.txt
viessmann_data_audit-0.1.8.dist-info/METADATA
viessmann_data_audit-0.1.8.dist-info/WHEEL
viessmann_data_audit-0.1.8.dist-info/top_level.txt
viessmann_data_audit-0.1.8.dist-info/RECORD
