Metadata-Version: 2.1
Name: viessmann-data-audit
Version: 0.1.8
Summary: Viessmann Data Audit
Home-page: UNKNOWN
Author: Viessmann
Author-email: ghlt@viessmann.com
License: MIT License
Download-URL: https://github.com/viessmann/viessmann_data_audit/archive/v0.1.8.tar.gz
Project-URL: Viessmann, https://www.linkedin.com/company/viessmann/
Project-URL: Source, https://github.com/viessmann/viessmann_data_audit
Keywords: data science
Platform: UNKNOWN
Classifier: Development Status :: 3 - Alpha
Classifier: License :: OSI Approved :: MIT License
Classifier: Programming Language :: Python :: 3.6
Classifier: Programming Language :: Python :: 3.7
Classifier: Topic :: Scientific/Engineering
Requires-Dist: pandas (>=0.22)
Requires-Dist: numpy (>=1.14)
Requires-Dist: scikit-learn (>=0.19)
Requires-Dist: seaborn (>=0.8.1)
